BrowseDrive/__init__.py
BrowseDrive/driverdownloader.py
BrowseDrive-2.2.dist-info/LICENSE
BrowseDrive-2.2.dist-info/METADATA
BrowseDrive-2.2.dist-info/WHEEL
BrowseDrive-2.2.dist-info/top_level.txt
BrowseDrive-2.2.dist-info/RECORD
