Metadata-Version: 2.1
Name: BrowseDrive
Version: 2.2
Summary: UNKNOWN
Home-page: UNKNOWN
License: UNKNOWN
Platform: UNKNOWN
Requires-Dist: requests (>=2.23.0)
Requires-Dist: bs4 (>=0.0.1)
